{"latetest_id": 8, "data": {"kanonkc": {"username": "KanonKC", "uid": "0001", "password": "1q2w3e4r", "score": 0}, "asdf": {"username": "ASDF", "uid": "0002", "password": "qwerty", "score": 1234}, "omg": {"username": "omg", "uid": "0000", "password": "omg1234", "score": 0}, "omg1": {"username": "omg1", "uid": "0001", "password": "omg1234", "score": 0}, "aaaaaaaaaaaaa": {"username": "aaaaaaaaaaaaa", "uid": "0002", "password": "omg1234", "score": 0}, "awdsawdsaw": {"username": "awdsawdsaw", "uid": "0004", "password": "omg1234", "score": 0}, "wdwdwdwd": {"username": "wdwdwdwd", "uid": "0005", "password": "omg1234", "score": 0}, "qbqb": {"username": "qbqb", "uid": "0006", "password": "123", "score": 0}, "hello": {"username": "Hello", "uid": "0007", "password": "World", "score": 0}}}